gurobi_modelanalyzer/__init__.py
gurobi_modelanalyzer/analyzer.py
gurobi_modelanalyzer/basic_analyzer.py
gurobi_modelanalyzer/common.py
gurobi_modelanalyzer/constraint_analyzer.py
gurobi_modelanalyzer/file_analyzer.py
gurobi_modelanalyzer/objective_function_analyzer.py
gurobi_modelanalyzer/results_analyzer.py
gurobi_modelanalyzer/solcheck.py
gurobi_modelanalyzer/variable_analyzer.py
gurobi_modelanalyzer-2.1.0.dist-info/METADATA
gurobi_modelanalyzer-2.1.0.dist-info/WHEEL
gurobi_modelanalyzer-2.1.0.dist-info/entry_points.txt
gurobi_modelanalyzer-2.1.0.dist-info/licenses/LICENSE
gurobi_modelanalyzer-2.1.0.dist-info/RECORD
