Metadata-Version: 2.3
Name: gurobi-modelanalyzer
Version: 2.1.0
Summary: Model analysis tools for explaining ill-conditioning and analyzing solutions.
Project-URL: Documentation, https://gurobi-modelanalyzer.readthedocs.io/en/latest/
Project-URL: Issues, https://github.com/Gurobi/gurobi-modelanalyzer/issues
Project-URL: Source, https://github.com/Gurobi/gurobi-modelanalyzer
Author-email: Ed Klotz <klotz@gurobi.com>, Greg Glockner <glockner@gurobi.com>
Keywords: optimization
Classifier: Development Status :: 4 - Beta
Classifier: Programming Language :: Python
Classifier: Programming Language :: Python :: 3.8
Classifier: Programming Language :: Python :: 3.9
Classifier: Programming Language :: Python :: 3.10
Classifier: Programming Language :: Python :: 3.11
Classifier: Programming Language :: Python :: Implementation :: CPython
Requires-Python: >=3.8
Requires-Dist: gurobipy
Requires-Dist: numpy
Provides-Extra: interactive
Requires-Dist: questionary; extra == 'interactive'
